README.md
pyloader.py
setup.py
lwe_pyloader.egg-info/PKG-INFO
lwe_pyloader.egg-info/SOURCES.txt
lwe_pyloader.egg-info/dependency_links.txt
lwe_pyloader.egg-info/requires.txt
lwe_pyloader.egg-info/top_level.txt