Metadata-Version: 1.1
Name: lwe-pyloader
Version: 1.2.4
Summary: A simple, easy to use, multithreaded downloader with queuing.
Home-page: https://github.com/linuxwhatelse/pyloader
Author: linuxwhatelse
Author-email: info@linuxwhatelse.de
License: GPLv3
Keywords: downloader threaded queuing
Platform: UNKNOWN
Classifier: Development Status :: 5 - Production/Stable
Classifier: Intended Audience :: Developers
Classifier: License :: OSI Approved :: GNU General Public License v3 (GPLv3)
Classifier: Operating System :: OS Independent
Classifier: Programming Language :: Python :: 2.7
Classifier: Programming Language :: Python :: 3
Classifier: Programming Language :: Python :: 3.4
Classifier: Programming Language :: Python :: 3.5
Classifier: Programming Language :: Python :: 3.6
Classifier: Programming Language :: Python :: 3.7
Classifier: Programming Language :: Python :: 3.8
Classifier: Topic :: Software Development :: Libraries :: Python Modules
